vks_bootstraper/__init__.py
vks_bootstraper/__main__.py
vks_bootstraper/metadata.py
vks_bootstraper/ssh_utils.py
vks_bootstraper-1.4.0.dist-info/LICENSE
vks_bootstraper-1.4.0.dist-info/METADATA
vks_bootstraper-1.4.0.dist-info/WHEEL
vks_bootstraper-1.4.0.dist-info/entry_points.txt
vks_bootstraper-1.4.0.dist-info/top_level.txt
vks_bootstraper-1.4.0.dist-info/RECORD
